pytchi/__init__.py
pytchi/pytchi.py
pytchi/lib/__init__.py
pytchi/lib/imgcc.py
pytchi/lib/ytdown.py
pytci/__init__.py
pytci/pytci.py
pytci/lib/__init__.py
pytci/lib/imgcc.py
pytci/lib/imgcc_avant_suppression_plt.py
pytci/lib/ytdown.py
pytchi-0.2.dist-info/METADATA
pytchi-0.2.dist-info/WHEEL
pytchi-0.2.dist-info/top_level.txt
pytchi-0.2.dist-info/RECORD
