Metadata-Version: 2.1
Name: pytchi
Version: 0.2
Summary: Python YouTube Concentric Circles Image
Home-page: https://github.com/cobacdavid/pytchi
Author: David COBAC
Author-email: david.cobac@gmail.com
License: CC-BY-NC-SA
Keywords: youtube,image,concentric,circle
Platform: UNKNOWN
Requires-Python: >3.6
Requires-Dist: pycairo
Requires-Dist: python-slugify
Requires-Dist: pytube
Requires-Dist: opencv-python-headless
